ivanov/__init__.py
ivanov/globals.py
ivanov/sascs.py
ivanov/sasma.py
ivanov/sasoa.py
ivanov/bo/__init__.py
ivanov/bo/bo.py
ivanov/sas/__init__.py
ivanov/sas/core.py
ivanov/sas/sascodes.py
ivanov/sas/utils.py
ivanov/vault/__init__.py
ivanov/vault/vault.py
ivanov/windows/__init__.py
ivanov/windows/taskparser.py
ivanov/windows/utils.py
ivanov-0.4.2.dist-info/LICENSE
ivanov-0.4.2.dist-info/METADATA
ivanov-0.4.2.dist-info/WHEEL
ivanov-0.4.2.dist-info/top_level.txt
ivanov-0.4.2.dist-info/RECORD
