Metadata-Version: 2.1
Name: ivanov
Version: 0.4.2
Summary: All sh*t in one place!
Home-page: https://github.com/GenericUser3/ivanov
Author: Yaroslav Ivanov
Author-email: mr.yaroslav.ivanov@gmail.com
Classifier: Programming Language :: Python :: 3
Classifier: Operating System :: OS Independent
Requires-Python: >=3.6
License-File: LICENSE
Requires-Dist: saspy
Requires-Dist: hvac
Requires-Dist: sqlparse
Requires-Dist: pythonnet (>=1.0) ; platform_system == "Windows"
